odoo/addons/mail_operating_unit/README.rst
odoo/addons/mail_operating_unit/__init__.py
odoo/addons/mail_operating_unit/__manifest__.py
odoo/addons/mail_operating_unit/demo/mail_operating_unit.xml
odoo/addons/mail_operating_unit/i18n/it.po
odoo/addons/mail_operating_unit/i18n/mail_operating_unit.pot
odoo/addons/mail_operating_unit/models/__init__.py
odoo/addons/mail_operating_unit/models/mail_template.py
odoo/addons/mail_operating_unit/models/models.py
odoo/addons/mail_operating_unit/models/operating_unit.py
odoo/addons/mail_operating_unit/readme/CONFIGURE.md
odoo/addons/mail_operating_unit/readme/CONTRIBUTORS.md
odoo/addons/mail_operating_unit/readme/DESCRIPTION.md
odoo/addons/mail_operating_unit/static/description/icon.png
odoo/addons/mail_operating_unit/static/description/index.html
odoo/addons/mail_operating_unit/tests/__init__.py
odoo/addons/mail_operating_unit/tests/common.py
odoo/addons/mail_operating_unit/tests/test_fake_partner_mail_operating_unit.py
odoo/addons/mail_operating_unit/tests/test_mail_operating_unit.py
odoo/addons/mail_operating_unit/tests/models/__init__.py
odoo/addons/mail_operating_unit/tests/models/fake_partner.py
odoo/addons/mail_operating_unit/views/mail_template.xml
odoo/addons/mail_operating_unit/views/operating_unit.xml
odoo_addon_mail_operating_unit-17.0.1.0.0.4.dist-info/METADATA
odoo_addon_mail_operating_unit-17.0.1.0.0.4.dist-info/WHEEL
odoo_addon_mail_operating_unit-17.0.1.0.0.4.dist-info/top_level.txt
odoo_addon_mail_operating_unit-17.0.1.0.0.4.dist-info/RECORD
